[
  {
    "artistName": "Gripin",
    "segment": "Moderate listeners"
  },
  {
    "artistName": "SZA",
    "segment": "Previously Active Listeners"
  },
  {
    "artistName": "Dove Cameron",
    "segment": "Previously Active Listeners"
  },
  {
    "artistName": "EMIN",
    "segment": "Light listeners"
  },
  {
    "artistName": "Alli Neumann",
    "segment": "Previously Active Listeners"
  },
  {
    "artistName": "Marcus Layton",
    "segment": "Previously Active Listeners"
  },
  {
    "artistName": "Malcolm Addey",
    "segment": "Moderate listeners"
  },
  {
    "artistName": "LOBODA",
    "segment": "Previously Active Listeners"
  },
  {
    "artistName": "Cem Adrian",
    "segment": "Previously Active Listeners"
  },
  {
    "artistName": "Sade",
    "segment": "Previously Active Listeners"
  },
  {
    "artistName": "Candan Erçetin",
    "segment": "Previously Active Listeners"
  },
  {
    "artistName": "Coldplay",
    "segment": "Previously Active Listeners"
  },
  {
    "artistName": "Valeriya",
    "segment": "Previously Active Listeners"
  },
  {
    "artistName": "Ali Biçim",
    "segment": "Previously Active Listeners"
  },
  {
    "artistName": "Joezi",
    "segment": "Previously Active Listeners"
  },
  {
    "artistName": "Alexander IV",
    "segment": "Previously Active Listeners"
  },
  {
    "artistName": "Demet Akalın",
    "segment": "Previously Active Listeners"
  },
  {
    "artistName": "RASA",
    "segment": "Moderate listeners"
  },
  {
    "artistName": "Johnny Blue Skies",
    "segment": "Previously Active Listeners"
  },
  {
    "artistName": "Funda Arar",
    "segment": "Light listeners"
  },
  {
    "artistName": "Miksu / Macloud",
    "segment": "Previously Active Listeners"
  },
  {
    "artistName": "Mert Demir",
    "segment": "Previously Active Listeners"
  },
  {
    "artistName": "lazy oscar",
    "segment": "Previously Active Listeners"
  },
  {
    "artistName": "jhfly",
    "segment": "Previously Active Listeners"
  },
  {
    "artistName": "Mustafa Ceceli",
    "segment": "Previously Active Listeners"
  },
  {
    "artistName": "A.L.I.S.O.N",
    "segment": "Super Listeners"
  },
  {
    "artistName": "Luminous",
    "segment": "Super Listeners"
  },
  {
    "artistName": "Alphaville",
    "segment": "Previously Active Listeners"
  },
  {
    "artistName": "Sean Paul",
    "segment": "Previously Active Listeners"
  },
  {
    "artistName": "The Weeknd",
    "segment": "Moderate listeners"
  },
  {
    "artistName": "Derya Uluğ",
    "segment": "Moderate listeners"
  },
  {
    "artistName": "byJ.",
    "segment": "Previously Active Listeners"
  },
  {
    "artistName": "Kendrick Lamar",
    "segment": "Previously Active Listeners"
  },
  {
    "artistName": "Goldband",
    "segment": "Light listeners"
  },
  {
    "artistName": "Feridun Düzağaç",
    "segment": "Previously Active Listeners"
  },
  {
    "artistName": "Gökhan Kırdar",
    "segment": "Previously Active Listeners"
  },
  {
    "artistName": "Basicboy",
    "segment": "Previously Active Listeners"
  },
  {
    "artistName": "Tinlicker",
    "segment": "Previously Active Listeners"
  },
  {
    "artistName": "Zvonkiy",
    "segment": "Light listeners"
  },
  {
    "artistName": "Tabitha",
    "segment": "Moderate listeners"
  },
  {
    "artistName": "Dermot Kennedy",
    "segment": "Previously Active Listeners"
  },
  {
    "artistName": "RIN",
    "segment": "Previously Active Listeners"
  },
  {
    "artistName": "D-Block Europe",
    "segment": "Previously Active Listeners"
  },
  {
    "artistName": "Zakkum",
    "segment": "Previously Active Listeners"
  },
  {
    "artistName": "İzel",
    "segment": "Previously Active Listeners"
  },
  {
    "artistName": "Lucio Dalla",
    "segment": "Previously Active Listeners"
  },
  {
    "artistName": "AVAION",
    "segment": "Previously Active Listeners"
  },
  {
    "artistName": "Travis Scott",
    "segment": "Previously Active Listeners"
  },
  {
    "artistName": "Giorgio Tuinfort",
    "segment": "Previously Active Listeners"
  },
  {
    "artistName": "BEGE",
    "segment": "Previously Active Listeners"
  },
  {
    "artistName": "ALIZADE",
    "segment": "Previously Active Listeners"
  },
  {
    "artistName": "Tame Impala",
    "segment": "Previously Active Listeners"
  },
  {
    "artistName": "Yellow Claw",
    "segment": "Previously Active Listeners"
  },
  {
    "artistName": "Rauf & Faik",
    "segment": "Moderate listeners"
  },
  {
    "artistName": "Yıldız Usmonova",
    "segment": "Previously Active Listeners"
  },
  {
    "artistName": "Ronnie Flex",
    "segment": "Previously Active Listeners"
  },
  {
    "artistName": "UZI",
    "segment": "Previously Active Listeners"
  },
  {
    "artistName": "48thSt",
    "segment": "Previously Active Listeners"
  },
  {
    "artistName": "Selda Bağcan",
    "segment": "Previously Active Listeners"
  },
  {
    "artistName": "Şebnem Ferah",
    "segment": "Previously Active Listeners"
  },
  {
    "artistName": "Artik & Asti",
    "segment": "Moderate listeners"
  },
  {
    "artistName": "KÖFN",
    "segment": "Previously Active Listeners"
  },
  {
    "artistName": "Jennifer Paige",
    "segment": "Previously Active Listeners"
  },
  {
    "artistName": "Bizzey",
    "segment": "Moderate listeners"
  },
  {
    "artistName": "John Newman",
    "segment": "Previously Active Listeners"
  },
  {
    "artistName": "Simge",
    "segment": "Light listeners"
  },
  {
    "artistName": "FEDUK",
    "segment": "Previously Active Listeners"
  },
  {
    "artistName": "Phil Woods",
    "segment": "Moderate listeners"
  },
  {
    "artistName": "Deauxnuts",
    "segment": "Previously Active Listeners"
  },
  {
    "artistName": "Jessie Reyez",
    "segment": "Previously Active Listeners"
  },
  {
    "artistName": "George Davidson",
    "segment": "Light listeners"
  },
  {
    "artistName": "COLCO",
    "segment": "Super Listeners"
  },
  {
    "artistName": "Ямаджи",
    "segment": "Moderate listeners"
  },
  {
    "artistName": "Kara Kross",
    "segment": "Light listeners"
  },
  {
    "artistName": "Tuğba Yurt",
    "segment": "Previously Active Listeners"
  },
  {
    "artistName": "Sebastian Kamae",
    "segment": "Previously Active Listeners"
  },
  {
    "artistName": "Guillaume Muschalle",
    "segment": "Previously Active Listeners"
  },
  {
    "artistName": "ALFA",
    "segment": "Previously Active Listeners"
  },
  {
    "artistName": "Jazzy",
    "segment": "Previously Active Listeners"
  },
  {
    "artistName": "Hande Ünsal",
    "segment": "Light listeners"
  },
  {
    "artistName": "Bonez MC",
    "segment": "Previously Active Listeners"
  },
  {
    "artistName": "Takeoff",
    "segment": "Previously Active Listeners"
  },
  {
    "artistName": "J. Rey Soul",
    "segment": "Previously Active Listeners"
  },
  {
    "artistName": "Maluma",
    "segment": "Previously Active Listeners"
  },
  {
    "artistName": "Mabel Matiz",
    "segment": "Light listeners"
  },
  {
    "artistName": "Heijan",
    "segment": "Previously Active Listeners"
  },
  {
    "artistName": "Ercüment Orkut",
    "segment": "Previously Active Listeners"
  },
  {
    "artistName": "Michael Naura Quartet",
    "segment": "Moderate listeners"
  },
  {
    "artistName": "Dave Brubeck",
    "segment": "Moderate listeners"
  },
  {
    "artistName": "Strehlow",
    "segment": "Previously Active Listeners"
  },
  {
    "artistName": "Zeynep Casalini",
    "segment": "Previously Active Listeners"
  },
  {
    "artistName": "Ebru Yaşar",
    "segment": "Previously Active Listeners"
  },
  {
    "artistName": "Adriano Celentano",
    "segment": "Previously Active Listeners"
  },
  {
    "artistName": "LIVE FREE",
    "segment": "Previously Active Listeners"
  },
  {
    "artistName": "Gökhan Türkmen",
    "segment": "Previously Active Listeners"
  },
  {
    "artistName": "Ludwig Göransson",
    "segment": "Moderate listeners"
  },
  {
    "artistName": "Misha Marvin",
    "segment": "Moderate listeners"
  },
  {
    "artistName": "Indila",
    "segment": "Previously Active Listeners"
  },
  {
    "artistName": "for you",
    "segment": "Previously Active Listeners"
  },
  {
    "artistName": "Navy Band",
    "segment": "Previously Active Listeners"
  },
  {
    "artistName": "DJ Shah",
    "segment": "Previously Active Listeners"
  },
  {
    "artistName": "Mary Gu",
    "segment": "Previously Active Listeners"
  },
  {
    "artistName": "Nilüfer",
    "segment": "Previously Active Listeners"
  },
  {
    "artistName": "Sena Şener",
    "segment": "Previously Active Listeners"
  },
  {
    "artistName": "Jah Khalib",
    "segment": "Light listeners"
  },
  {
    "artistName": "Freddie Hubbard",
    "segment": "Moderate listeners"
  },
  {
    "artistName": "Black Eyed Peas",
    "segment": "Previously Active Listeners"
  },
  {
    "artistName": "Yüksek Sadakat",
    "segment": "Previously Active Listeners"
  },
  {
    "artistName": "Ziynet Sali",
    "segment": "Moderate listeners"
  },
  {
    "artistName": "Yüzyüzeyken Konuşuruz",
    "segment": "Light listeners"
  },
  {
    "artistName": "Lemongrass",
    "segment": "Previously Active Listeners"
  },
  {
    "artistName": "B-Side",
    "segment": "Previously Active Listeners"
  },
  {
    "artistName": "Tove Lo",
    "segment": "Previously Active Listeners"
  },
  {
    "artistName": "Chase & Status",
    "segment": "Previously Active Listeners"
  },
  {
    "artistName": "Ajda Pekkan",
    "segment": "Previously Active Listeners"
  },
  {
    "artistName": "Gzuz",
    "segment": "Previously Active Listeners"
  },
  {
    "artistName": "GAYAZOV$ BROTHER$",
    "segment": "Previously Active Listeners"
  },
  {
    "artistName": "Chris Mazuera",
    "segment": "Super Listeners"
  },
  {
    "artistName": "Фейджи",
    "segment": "Moderate listeners"
  },
  {
    "artistName": "Rast",
    "segment": "Previously Active Listeners"
  },
  {
    "artistName": "Kolpa",
    "segment": "Moderate listeners"
  },
  {
    "artistName": "Gürkan Uygun",
    "segment": "Previously Active Listeners"
  },
  {
    "artistName": "Gaetano Donizetti",
    "segment": "Previously Active Listeners"
  },
  {
    "artistName": "Murat Boz",
    "segment": "Previously Active Listeners"
  },
  {
    "artistName": "Ella Henderson",
    "segment": "Previously Active Listeners"
  },
  {
    "artistName": "Galantis",
    "segment": "Previously Active Listeners"
  },
  {
    "artistName": "Ariana Grande",
    "segment": "Previously Active Listeners"
  },
  {
    "artistName": "Korey Wade",
    "segment": "Previously Active Listeners"
  },
  {
    "artistName": "Cengiz Kurtoğlu",
    "segment": "Previously Active Listeners"
  },
  {
    "artistName": "Halodayı",
    "segment": "Previously Active Listeners"
  },
  {
    "artistName": "James Horner",
    "segment": "Moderate listeners"
  },
  {
    "artistName": "Helsloot",
    "segment": "Previously Active Listeners"
  },
  {
    "artistName": "Berezy",
    "segment": "Previously Active Listeners"
  },
  {
    "artistName": "Barış Manço",
    "segment": "Previously Active Listeners"
  },
  {
    "artistName": "David Puentez",
    "segment": "Previously Active Listeners"
  },
  {
    "artistName": "The Avener",
    "segment": "Previously Active Listeners"
  },
  {
    "artistName": "Ezginin Günlügü",
    "segment": "Previously Active Listeners"
  },
  {
    "artistName": "Leona Lewis",
    "segment": "Previously Active Listeners"
  },
  {
    "artistName": "BLOK3",
    "segment": "Previously Active Listeners"
  },
  {
    "artistName": "Doechii",
    "segment": "Previously Active Listeners"
  },
  {
    "artistName": "Didier Pieri",
    "segment": "Previously Active Listeners"
  },
  {
    "artistName": "Melek Mosso",
    "segment": "Previously Active Listeners"
  },
  {
    "artistName": "Ömer Bükülmezoğlu",
    "segment": "Previously Active Listeners"
  },
  {
    "artistName": "Dedublüman",
    "segment": "Previously Active Listeners"
  },
  {
    "artistName": "midnite library",
    "segment": "Previously Active Listeners"
  },
  {
    "artistName": "Andriy Yurkevych",
    "segment": "Previously Active Listeners"
  },
  {
    "artistName": "Imperial Chorus",
    "segment": "Previously Active Listeners"
  },
  {
    "artistName": "T V S N",
    "segment": "Previously Active Listeners"
  },
  {
    "artistName": "Hande Mehan",
    "segment": "Previously Active Listeners"
  },
  {
    "artistName": "kavabanga Depo kolibri",
    "segment": "Light listeners"
  },
  {
    "artistName": "Maan",
    "segment": "Moderate listeners"
  },
  {
    "artistName": "Sugar Cane Davis",
    "segment": "Previously Active Listeners"
  },
  {
    "artistName": "Chris Brown",
    "segment": "Previously Active Listeners"
  },
  {
    "artistName": "Tyga",
    "segment": "Previously Active Listeners"
  },
  {
    "artistName": "Céline Dion",
    "segment": "Moderate listeners"
  },
  {
    "artistName": "Snelle",
    "segment": "Moderate listeners"
  },
  {
    "artistName": "Murat Göğebakan",
    "segment": "Light listeners"
  },
  {
    "artistName": "Jack DeJohnette",
    "segment": "Moderate listeners"
  },
  {
    "artistName": "Duan Wasi",
    "segment": "Previously Active Listeners"
  },
  {
    "artistName": "El Alfa",
    "segment": "Previously Active Listeners"
  },
  {
    "artistName": "Diplo",
    "segment": "Previously Active Listeners"
  },
  {
    "artistName": "Barcelona",
    "segment": "Previously Active Listeners"
  },
  {
    "artistName": "İrem Derici",
    "segment": "Previously Active Listeners"
  },
  {
    "artistName": "Denizou",
    "segment": "Previously Active Listeners"
  },
  {
    "artistName": "Orchid City",
    "segment": "Super Listeners"
  },
  {
    "artistName": "Arem Ozguc",
    "segment": "Previously Active Listeners"
  },
  {
    "artistName": "Skeptika",
    "segment": "Previously Active Listeners"
  },
  {
    "artistName": "Maxwell",
    "segment": "Previously Active Listeners"
  },
  {
    "artistName": ".Sinh",
    "segment": "Super Listeners"
  },
  {
    "artistName": "Calvin Harris",
    "segment": "Previously Active Listeners"
  },
  {
    "artistName": "Anitta",
    "segment": "Previously Active Listeners"
  },
  {
    "artistName": "Adele",
    "segment": "Previously Active Listeners"
  },
  {
    "artistName": "HammAli",
    "segment": "Light listeners"
  },
  {
    "artistName": "Los Cuates de Sinaloa",
    "segment": "Light listeners"
  },
  {
    "artistName": "Ceza",
    "segment": "Previously Active Listeners"
  },
  {
    "artistName": "Alesso",
    "segment": "Previously Active Listeners"
  },
  {
    "artistName": "Marconi Union",
    "segment": "Previously Active Listeners"
  },
  {
    "artistName": "Hans Zimmer",
    "segment": "Previously Active Listeners"
  },
  {
    "artistName": "LAUWE",
    "segment": "Previously Active Listeners"
  },
  {
    "artistName": "MAX BARSKIH",
    "segment": "Moderate listeners"
  },
  {
    "artistName": "Elton John",
    "segment": "Previously Active Listeners"
  },
  {
    "artistName": "Kâzım Koyuncu",
    "segment": "Previously Active Listeners"
  },
  {
    "artistName": "Asketa & Natan Chaim",
    "segment": "Previously Active Listeners"
  },
  {
    "artistName": "Ahmet Kaya",
    "segment": "Previously Active Listeners"
  },
  {
    "artistName": "Evgeny Grinko",
    "segment": "Light listeners"
  },
  {
    "artistName": "The Saturdays",
    "segment": "Previously Active Listeners"
  },
  {
    "artistName": "Halsey",
    "segment": "Previously Active Listeners"
  },
  {
    "artistName": "Sibel Can",
    "segment": "Previously Active Listeners"
  },
  {
    "artistName": "Jennifer Lopez",
    "segment": "Previously Active Listeners"
  },
  {
    "artistName": "Various Artists",
    "segment": "Super Listeners"
  },
  {
    "artistName": "Manuel Riva",
    "segment": "Previously Active Listeners"
  },
  {
    "artistName": "Killersprotte",
    "segment": "Previously Active Listeners"
  },
  {
    "artistName": "Chick Corea",
    "segment": "Super Listeners"
  },
  {
    "artistName": "Bahadır Sağlam",
    "segment": "Moderate listeners"
  },
  {
    "artistName": "KitschKrieg",
    "segment": "Previously Active Listeners"
  },
  {
    "artistName": "Elena Temnikova",
    "segment": "Light listeners"
  },
  {
    "artistName": "JONY",
    "segment": "Super Listeners"
  },
  {
    "artistName": "Key Glock",
    "segment": "Previously Active Listeners"
  },
  {
    "artistName": "Doğu Swag",
    "segment": "Light listeners"
  },
  {
    "artistName": "John Coltrane",
    "segment": "Moderate listeners"
  },
  {
    "artistName": "Sharks Deli",
    "segment": "Super Listeners"
  },
  {
    "artistName": "MonoType",
    "segment": "Previously Active Listeners"
  },
  {
    "artistName": "Dabro",
    "segment": "Light listeners"
  },
  {
    "artistName": "Mari Kraimbrery",
    "segment": "Moderate listeners"
  },
  {
    "artistName": "Burak Yeter",
    "segment": "Previously Active Listeners"
  },
  {
    "artistName": "МОТ",
    "segment": "Moderate listeners"
  },
  {
    "artistName": "Lusia Chebotina",
    "segment": "Light listeners"
  },
  {
    "artistName": "Kadebostany",
    "segment": "Previously Active Listeners"
  },
  {
    "artistName": "Sezen Aksu",
    "segment": "Moderate listeners"
  },
  {
    "artistName": "Screen Jazzmaster",
    "segment": "Super Listeners"
  },
  {
    "artistName": "Bergen",
    "segment": "Previously Active Listeners"
  },
  {
    "artistName": "Slide Hampton",
    "segment": "Moderate listeners"
  },
  {
    "artistName": "Kavv",
    "segment": "Previously Active Listeners"
  },
  {
    "artistName": "Future",
    "segment": "Previously Active Listeners"
  },
  {
    "artistName": "Sam Cosmo",
    "segment": "Previously Active Listeners"
  },
  {
    "artistName": "Hara Noda",
    "segment": "Moderate listeners"
  },
  {
    "artistName": "M4RSS",
    "segment": "Previously Active Listeners"
  },
  {
    "artistName": "Veysel",
    "segment": "Previously Active Listeners"
  },
  {
    "artistName": "Little Mix",
    "segment": "Previously Active Listeners"
  },
  {
    "artistName": "NAZIMA",
    "segment": "Previously Active Listeners"
  },
  {
    "artistName": "Gio Pika",
    "segment": "Previously Active Listeners"
  },
  {
    "artistName": "Özcan Deniz",
    "segment": "Previously Active Listeners"
  },
  {
    "artistName": "Swedish House Mafia",
    "segment": "Previously Active Listeners"
  },
  {
    "artistName": "Duman",
    "segment": "Previously Active Listeners"
  },
  {
    "artistName": "Rudimental",
    "segment": "Previously Active Listeners"
  },
  {
    "artistName": "Maxim Fadeev",
    "segment": "Previously Active Listeners"
  },
  {
    "artistName": "Levent Yüksel",
    "segment": "Previously Active Listeners"
  },
  {
    "artistName": "Ferhat Göçer",
    "segment": "Previously Active Listeners"
  },
  {
    "artistName": "Oscar Peterson Trio",
    "segment": "Super Listeners"
  },
  {
    "artistName": "Güllü",
    "segment": "Previously Active Listeners"
  },
  {
    "artistName": "Big Sean",
    "segment": "Previously Active Listeners"
  },
  {
    "artistName": "Aytekin Kurt",
    "segment": "Previously Active Listeners"
  },
  {
    "artistName": "Calming Hearts",
    "segment": "Super Listeners"
  },
  {
    "artistName": "Sturgill Simpson",
    "segment": "Previously Active Listeners"
  },
  {
    "artistName": "Giorgia",
    "segment": "Previously Active Listeners"
  },
  {
    "artistName": "Dardan",
    "segment": "Moderate listeners"
  },
  {
    "artistName": "Kodak Black",
    "segment": "Previously Active Listeners"
  },
  {
    "artistName": "Jason Derulo",
    "segment": "Previously Active Listeners"
  },
  {
    "artistName": "jacuzzi jefferson",
    "segment": "Super Listeners"
  },
  {
    "artistName": "Sertab Erener",
    "segment": "Previously Active Listeners"
  },
  {
    "artistName": "Loredana",
    "segment": "Previously Active Listeners"
  },
  {
    "artistName": "Can Gox",
    "segment": "Previously Active Listeners"
  },
  {
    "artistName": "Rihanna",
    "segment": "Previously Active Listeners"
  },
  {
    "artistName": "Burcu Güneş",
    "segment": "Previously Active Listeners"
  },
  {
    "artistName": "Ilkay Sencan",
    "segment": "Previously Active Listeners"
  },
  {
    "artistName": "Consuelo Velázquez",
    "segment": "Light listeners"
  },
  {
    "artistName": "Constantine",
    "segment": "Super Listeners"
  },
  {
    "artistName": "Tiësto",
    "segment": "Previously Active Listeners"
  },
  {
    "artistName": "Summer Cem",
    "segment": "Previously Active Listeners"
  },
  {
    "artistName": "Imperial Orchestra",
    "segment": "Previously Active Listeners"
  },
  {
    "artistName": "Jamule",
    "segment": "Previously Active Listeners"
  },
  {
    "artistName": "Sagopa Kajmer",
    "segment": "Previously Active Listeners"
  },
  {
    "artistName": "Nej",
    "segment": "Previously Active Listeners"
  },
  {
    "artistName": "Kalwi & Remi",
    "segment": "Previously Active Listeners"
  },
  {
    "artistName": "Majeste",
    "segment": "Previously Active Listeners"
  },
  {
    "artistName": "TONI",
    "segment": "Light listeners"
  },
  {
    "artistName": "Jax Jones",
    "segment": "Previously Active Listeners"
  },
  {
    "artistName": "Rompasso",
    "segment": "Moderate listeners"
  },
  {
    "artistName": "Lou Donaldson",
    "segment": "Moderate listeners"
  },
  {
    "artistName": "Boyan",
    "segment": "Previously Active Listeners"
  },
  {
    "artistName": "KIDDO",
    "segment": "Previously Active Listeners"
  },
  {
    "artistName": "Mars Deimos",
    "segment": "Moderate listeners"
  },
  {
    "artistName": "LX",
    "segment": "Previously Active Listeners"
  },
  {
    "artistName": "Bayhan",
    "segment": "Previously Active Listeners"
  },
  {
    "artistName": "Keith Jarrett",
    "segment": "Moderate listeners"
  },
  {
    "artistName": "Meraki",
    "segment": "Previously Active Listeners"
  },
  {
    "artistName": "DAVI JUNO",
    "segment": "Previously Active Listeners"
  },
  {
    "artistName": "Gucci Mane",
    "segment": "Previously Active Listeners"
  },
  {
    "artistName": "Herbie Mann",
    "segment": "Moderate listeners"
  },
  {
    "artistName": "Don Omar",
    "segment": "Previously Active Listeners"
  },
  {
    "artistName": "oofoe",
    "segment": "Previously Active Listeners"
  },
  {
    "artistName": "ZeddMusique",
    "segment": "Previously Active Listeners"
  },
  {
    "artistName": "Грибы",
    "segment": "Previously Active Listeners"
  },
  {
    "artistName": "Years & Years",
    "segment": "Previously Active Listeners"
  },
  {
    "artistName": "Müslüm Gürses",
    "segment": "Light listeners"
  },
  {
    "artistName": "Airstream",
    "segment": "Super Listeners"
  },
  {
    "artistName": "HammAli & Navai",
    "segment": "Moderate listeners"
  },
  {
    "artistName": "Simon Franglen",
    "segment": "Previously Active Listeners"
  },
  {
    "artistName": "Eylem Aktaş",
    "segment": "Previously Active Listeners"
  },
  {
    "artistName": "Mark Eliyahu",
    "segment": "Previously Active Listeners"
  },
  {
    "artistName": "Ramil'",
    "segment": "Light listeners"
  },
  {
    "artistName": "Bushido",
    "segment": "Previously Active Listeners"
  },
  {
    "artistName": "Disciples",
    "segment": "Previously Active Listeners"
  },
  {
    "artistName": "Taio Cruz",
    "segment": "Previously Active Listeners"
  },
  {
    "artistName": "LOUNGETUNES",
    "segment": "Super Listeners"
  },
  {
    "artistName": "Mavzer Tabancas",
    "segment": "Previously Active Listeners"
  },
  {
    "artistName": "Theo",
    "segment": "Previously Active Listeners"
  },
  {
    "artistName": "Becky Hill",
    "segment": "Previously Active Listeners"
  },
  {
    "artistName": "SP-Mato",
    "segment": "Previously Active Listeners"
  },
  {
    "artistName": "INJI",
    "segment": "Previously Active Listeners"
  },
  {
    "artistName": "Sandy Mental",
    "segment": "Previously Active Listeners"
  },
  {
    "artistName": "Horscht",
    "segment": "Previously Active Listeners"
  },
  {
    "artistName": "Orchestra del Teatro Carlo Felice di Genova",
    "segment": "Previously Active Listeners"
  },
  {
    "artistName": "Hotel Pools",
    "segment": "Super Listeners"
  },
  {
    "artistName": "Madonna",
    "segment": "Previously Active Listeners"
  },
  {
    "artistName": "NILETTO",
    "segment": "Moderate listeners"
  },
  {
    "artistName": "George Thorogood & The Destroyers",
    "segment": "Previously Active Listeners"
  },
  {
    "artistName": "Trettmann",
    "segment": "Previously Active Listeners"
  },
  {
    "artistName": "Pitbull",
    "segment": "Previously Active Listeners"
  },
  {
    "artistName": "Gary Peacock",
    "segment": "Moderate listeners"
  },
  {
    "artistName": "a-ha",
    "segment": "Previously Active Listeners"
  },
  {
    "artistName": "emre aydın",
    "segment": "Moderate listeners"
  },
  {
    "artistName": "ZAYN",
    "segment": "Previously Active Listeners"
  },
  {
    "artistName": "Erkin Koray",
    "segment": "Previously Active Listeners"
  },
  {
    "artistName": "Abra Cadabra",
    "segment": "Previously Active Listeners"
  },
  {
    "artistName": "Juju",
    "segment": "Moderate listeners"
  },
  {
    "artistName": "NIVESTA",
    "segment": "Previously Active Listeners"
  },
  {
    "artistName": "VERBEE",
    "segment": "Light listeners"
  },
  {
    "artistName": "Mehmet Güreli",
    "segment": "Previously Active Listeners"
  },
  {
    "artistName": "Jonas Blue",
    "segment": "Previously Active Listeners"
  },
  {
    "artistName": "Arman Aydin",
    "segment": "Previously Active Listeners"
  },
  {
    "artistName": "HANNA",
    "segment": "Moderate listeners"
  },
  {
    "artistName": "Solstice Beats",
    "segment": "Previously Active Listeners"
  },
  {
    "artistName": "Ne-Yo",
    "segment": "Previously Active Listeners"
  },
  {
    "artistName": "Troye Sivan",
    "segment": "Previously Active Listeners"
  },
  {
    "artistName": "Casein",
    "segment": "Previously Active Listeners"
  },
  {
    "artistName": "Göksel",
    "segment": "Previously Active Listeners"
  },
  {
    "artistName": "Duke Ellington",
    "segment": "Moderate listeners"
  },
  {
    "artistName": "MEDUZA",
    "segment": "Previously Active Listeners"
  },
  {
    "artistName": "Moledro",
    "segment": "Super Listeners"
  },
  {
    "artistName": "Zeynep Dizdar",
    "segment": "Previously Active Listeners"
  },
  {
    "artistName": "Luciano Pavarotti",
    "segment": "Previously Active Listeners"
  },
  {
    "artistName": "Drenchill",
    "segment": "Previously Active Listeners"
  },
  {
    "artistName": "070 Shake",
    "segment": "Previously Active Listeners"
  },
  {
    "artistName": "Ahmed Shad",
    "segment": "Moderate listeners"
  },
  {
    "artistName": "Egor Kreed",
    "segment": "Light listeners"
  },
  {
    "artistName": "Kutluay production music",
    "segment": "Previously Active Listeners"
  },
  {
    "artistName": "Mahmut Orhan",
    "segment": "Previously Active Listeners"
  },
  {
    "artistName": "Metro Boomin",
    "segment": "Previously Active Listeners"
  },
  {
    "artistName": "Harry Hawaii",
    "segment": "Previously Active Listeners"
  },
  {
    "artistName": "farewell",
    "segment": "Previously Active Listeners"
  },
  {
    "artistName": "Erdem Kınay",
    "segment": "Previously Active Listeners"
  },
  {
    "artistName": "Rita Ora",
    "segment": "Previously Active Listeners"
  },
  {
    "artistName": "Ramzan Abitov",
    "segment": "Moderate listeners"
  },
  {
    "artistName": "Quavo",
    "segment": "Previously Active Listeners"
  },
  {
    "artistName": "Enrique Iglesias",
    "segment": "Previously Active Listeners"
  },
  {
    "artistName": "Joe Pass",
    "segment": "Moderate listeners"
  },
  {
    "artistName": "Mazhar Alanson",
    "segment": "Previously Active Listeners"
  },
  {
    "artistName": "SFR",
    "segment": "Previously Active Listeners"
  },
  {
    "artistName": "Cihan Mürtezaoğlu",
    "segment": "Previously Active Listeners"
  },
  {
    "artistName": "Jobii",
    "segment": "Super Listeners"
  },
  {
    "artistName": "Toygar Işıklı",
    "segment": "Previously Active Listeners"
  },
  {
    "artistName": "Azerin",
    "segment": "Previously Active Listeners"
  },
  {
    "artistName": "Model",
    "segment": "Previously Active Listeners"
  },
  {
    "artistName": "Iggy Azalea",
    "segment": "Previously Active Listeners"
  },
  {
    "artistName": "Secret Garden",
    "segment": "Light listeners"
  },
  {
    "artistName": "Wonkerz",
    "segment": "Previously Active Listeners"
  },
  {
    "artistName": "Basta",
    "segment": "Light listeners"
  },
  {
    "artistName": "Andrea Bocelli",
    "segment": "Moderate listeners"
  },
  {
    "artistName": "Aslı Güngör",
    "segment": "Previously Active Listeners"
  },
  {
    "artistName": "Federiko",
    "segment": "Previously Active Listeners"
  },
  {
    "artistName": "Ellie Goulding",
    "segment": "Previously Active Listeners"
  },
  {
    "artistName": "Ozuna",
    "segment": "Previously Active Listeners"
  },
  {
    "artistName": "Smoke Trees",
    "segment": "Previously Active Listeners"
  },
  {
    "artistName": "hope mona",
    "segment": "Previously Active Listeners"
  },
  {
    "artistName": "RAF Camora",
    "segment": "Previously Active Listeners"
  },
  {
    "artistName": "Klava Koka",
    "segment": "Previously Active Listeners"
  },
  {
    "artistName": "Snoop Dogg",
    "segment": "Previously Active Listeners"
  },
  {
    "artistName": "Andro",
    "segment": "Light listeners"
  },
  {
    "artistName": "Joel Corry",
    "segment": "Previously Active Listeners"
  },
  {
    "artistName": "Ozan Çolakoğlu",
    "segment": "Moderate listeners"
  },
  {
    "artistName": "Bruno Mars",
    "segment": "Previously Active Listeners"
  },
  {
    "artistName": "FLKS",
    "segment": "Previously Active Listeners"
  },
  {
    "artistName": "IRAIDA",
    "segment": "Previously Active Listeners"
  },
  {
    "artistName": "JANAGA",
    "segment": "Light listeners"
  },
  {
    "artistName": "Toto Cutugno",
    "segment": "Moderate listeners"
  },
  {
    "artistName": "Turac Berkay",
    "segment": "Previously Active Listeners"
  },
  {
    "artistName": "luv pug",
    "segment": "Previously Active Listeners"
  },
  {
    "artistName": "David Wingo",
    "segment": "Previously Active Listeners"
  },
  {
    "artistName": "Kygo",
    "segment": "Previously Active Listeners"
  },
  {
    "artistName": "Frédéric Riesterer",
    "segment": "Previously Active Listeners"
  },
  {
    "artistName": "Barış Akarsu",
    "segment": "Light listeners"
  },
  {
    "artistName": "Zoë Tauran",
    "segment": "Previously Active Listeners"
  },
  {
    "artistName": "Zoe Saldana",
    "segment": "Previously Active Listeners"
  },
  {
    "artistName": "Ka-Re",
    "segment": "Moderate listeners"
  },
  {
    "artistName": "PHARAOH",
    "segment": "Previously Active Listeners"
  },
  {
    "artistName": "Ava Max",
    "segment": "Previously Active Listeners"
  },
  {
    "artistName": "Dua Lipa",
    "segment": "Previously Active Listeners"
  },
  {
    "artistName": "Borqy",
    "segment": "Previously Active Listeners"
  },
  {
    "artistName": "Seksendört",
    "segment": "Moderate listeners"
  },
  {
    "artistName": "G-Eazy",
    "segment": "Previously Active Listeners"
  },
  {
    "artistName": "Plusma",
    "segment": "Previously Active Listeners"
  },
  {
    "artistName": "John Martin",
    "segment": "Previously Active Listeners"
  },
  {
    "artistName": "Cat Paw",
    "segment": "Previously Active Listeners"
  },
  {
    "artistName": "Zivert",
    "segment": "Moderate listeners"
  },
  {
    "artistName": "Pixie Dust",
    "segment": "Super Listeners"
  },
  {
    "artistName": "Parson James",
    "segment": "Previously Active Listeners"
  },
  {
    "artistName": "Gülşen",
    "segment": "Previously Active Listeners"
  },
  {
    "artistName": "Rick Astley",
    "segment": "Previously Active Listeners"
  },
  {
    "artistName": "Berksan",
    "segment": "Previously Active Listeners"
  },
  {
    "artistName": "USHER",
    "segment": "Previously Active Listeners"
  },
  {
    "artistName": "Parov Stelar",
    "segment": "Previously Active Listeners"
  },
  {
    "artistName": "Ebru Gündeş",
    "segment": "Previously Active Listeners"
  },
  {
    "artistName": "Albert Neve",
    "segment": "Previously Active Listeners"
  },
  {
    "artistName": "KC Rebell",
    "segment": "Moderate listeners"
  },
  {
    "artistName": "Yıldız Tilbe",
    "segment": "Previously Active Listeners"
  },
  {
    "artistName": "Pharrell Williams",
    "segment": "Previously Active Listeners"
  },
  {
    "artistName": "Cem Tuncer",
    "segment": "Previously Active Listeners"
  },
  {
    "artistName": "Louis Armstrong",
    "segment": "Moderate listeners"
  },
  {
    "artistName": "Dweeb",
    "segment": "Previously Active Listeners"
  },
  {
    "artistName": "Loreen",
    "segment": "Previously Active Listeners"
  },
  {
    "artistName": "ANIVAR",
    "segment": "Light listeners"
  },
  {
    "artistName": "C418",
    "segment": "Super Listeners"
  },
  {
    "artistName": "DEMET ELLOO",
    "segment": "Previously Active Listeners"
  },
  {
    "artistName": "mor ve ötesi",
    "segment": "Previously Active Listeners"
  },
  {
    "artistName": "TommyMuzzic",
    "segment": "Previously Active Listeners"
  },
  {
    "artistName": "Benny Benassi",
    "segment": "Previously Active Listeners"
  },
  {
    "artistName": "Graham Candy",
    "segment": "Previously Active Listeners"
  },
  {
    "artistName": "Bebe Rexha",
    "segment": "Previously Active Listeners"
  },
  {
    "artistName": "Martin Garrix",
    "segment": "Previously Active Listeners"
  },
  {
    "artistName": "Kim Petras",
    "segment": "Previously Active Listeners"
  },
  {
    "artistName": "Pape Diouf",
    "segment": "Previously Active Listeners"
  },
  {
    "artistName": "MATRANG",
    "segment": "Moderate listeners"
  },
  {
    "artistName": "Playboi Carti",
    "segment": "Previously Active Listeners"
  },
  {
    "artistName": "Apache 207",
    "segment": "Moderate listeners"
  },
  {
    "artistName": "Peggy Gou",
    "segment": "Previously Active Listeners"
  },
  {
    "artistName": "Kargo",
    "segment": "Moderate listeners"
  },
  {
    "artistName": "Fiva Bros",
    "segment": "Super Listeners"
  },
  {
    "artistName": "Capital Bra",
    "segment": "Previously Active Listeners"
  },
  {
    "artistName": "Dexter Gordon",
    "segment": "Moderate listeners"
  },
  {
    "artistName": "MAW",
    "segment": "Previously Active Listeners"
  },
  {
    "artistName": "Matteo Bocelli",
    "segment": "Previously Active Listeners"
  },
  {
    "artistName": "Brooklyn Duo",
    "segment": "Light listeners"
  },
  {
    "artistName": "PNAU",
    "segment": "Previously Active Listeners"
  },
  {
    "artistName": "Viktor Minsky",
    "segment": "Previously Active Listeners"
  },
  {
    "artistName": "Sia",
    "segment": "Previously Active Listeners"
  },
  {
    "artistName": "David Guetta",
    "segment": "Previously Active Listeners"
  },
  {
    "artistName": "dryhope",
    "segment": "Previously Active Listeners"
  },
  {
    "artistName": "Stefano Antonucci",
    "segment": "Previously Active Listeners"
  },
  {
    "artistName": "Goodboys",
    "segment": "Previously Active Listeners"
  },
  {
    "artistName": "Çelik",
    "segment": "Previously Active Listeners"
  },
  {
    "artistName": "КУЧЕР",
    "segment": "Light listeners"
  },
  {
    "artistName": "Beyoncé",
    "segment": "Previously Active Listeners"
  },
  {
    "artistName": "Camila Cabello",
    "segment": "Previously Active Listeners"
  },
  {
    "artistName": "Kris Kross Amsterdam",
    "segment": "Moderate listeners"
  },
  {
    "artistName": "Alan Walker",
    "segment": "Previously Active Listeners"
  },
  {
    "artistName": "MONA",
    "segment": "Light listeners"
  },
  {
    "artistName": "RSAC",
    "segment": "Moderate listeners"
  },
  {
    "artistName": "Chancla",
    "segment": "Previously Active Listeners"
  },
  {
    "artistName": "Güneş",
    "segment": "Previously Active Listeners"
  },
  {
    "artistName": "Helyos",
    "segment": "Previously Active Listeners"
  },
  {
    "artistName": "2hermanoz",
    "segment": "Previously Active Listeners"
  },
  {
    "artistName": "DJ SMASH",
    "segment": "Previously Active Listeners"
  },
  {
    "artistName": "Faithless",
    "segment": "Previously Active Listeners"
  },
  {
    "artistName": "Efe Çınar",
    "segment": "Previously Active Listeners"
  },
  {
    "artistName": "Coco",
    "segment": "Previously Active Listeners"
  },
  {
    "artistName": "Mustafa Sandal",
    "segment": "Previously Active Listeners"
  },
  {
    "artistName": "Niklouds",
    "segment": "Previously Active Listeners"
  },
  {
    "artistName": "Midnight Daydream",
    "segment": "Previously Active Listeners"
  },
  {
    "artistName": "Deeb",
    "segment": "Previously Active Listeners"
  },
  {
    "artistName": "Nora & Chris",
    "segment": "Previously Active Listeners"
  },
  {
    "artistName": "Ilkan Gunuc",
    "segment": "Moderate listeners"
  },
  {
    "artistName": "Kubilay Karça",
    "segment": "Previously Active Listeners"
  },
  {
    "artistName": "Baen Mow",
    "segment": "Previously Active Listeners"
  },
  {
    "artistName": "Rafet El Roman",
    "segment": "Moderate listeners"
  },
  {
    "artistName": "Bengü",
    "segment": "Previously Active Listeners"
  },
  {
    "artistName": "Ufo361",
    "segment": "Previously Active Listeners"
  },
  {
    "artistName": "Reynmen",
    "segment": "Previously Active Listeners"
  },
  {
    "artistName": "Linet",
    "segment": "Previously Active Listeners"
  },
  {
    "artistName": "Tarkan",
    "segment": "Moderate listeners"
  },
  {
    "artistName": "GLOFLY",
    "segment": "Super Listeners"
  },
  {
    "artistName": "Eldzhey",
    "segment": "Light listeners"
  },
  {
    "artistName": "RAYE",
    "segment": "Previously Active Listeners"
  },
  {
    "artistName": "Lesha Svik",
    "segment": "Light listeners"
  },
  {
    "artistName": "Sam Smith",
    "segment": "Previously Active Listeners"
  },
  {
    "artistName": "Nymano",
    "segment": "Super Listeners"
  },
  {
    "artistName": "Sting",
    "segment": "Moderate listeners"
  },
  {
    "artistName": "Ayşegül Aldinç",
    "segment": "Previously Active Listeners"
  },
  {
    "artistName": "Semicenk",
    "segment": "Moderate listeners"
  },
  {
    "artistName": "Max Melvin",
    "segment": "Super Listeners"
  },
  {
    "artistName": "Massaman",
    "segment": "Super Listeners"
  },
  {
    "artistName": "Alok",
    "segment": "Previously Active Listeners"
  },
  {
    "artistName": "Hurts",
    "segment": "Previously Active Listeners"
  },
  {
    "artistName": "Migos",
    "segment": "Previously Active Listeners"
  },
  {
    "artistName": "Mary Lou Williams",
    "segment": "Moderate listeners"
  },
  {
    "artistName": "Enya",
    "segment": "Moderate listeners"
  },
  {
    "artistName": "IVAN VALEEV",
    "segment": "Moderate listeners"
  },
  {
    "artistName": "linanthem",
    "segment": "Super Listeners"
  },
  {
    "artistName": "Zeynep Bastık",
    "segment": "Previously Active Listeners"
  },
  {
    "artistName": "Colonel Bagshot",
    "segment": "Previously Active Listeners"
  },
  {
    "artistName": "Oaty.",
    "segment": "Previously Active Listeners"
  },
  {
    "artistName": "Mozzik",
    "segment": "Previously Active Listeners"
  },
  {
    "artistName": "Grivina",
    "segment": "Moderate listeners"
  },
  {
    "artistName": "cassö",
    "segment": "Previously Active Listeners"
  },
  {
    "artistName": "Mabel",
    "segment": "Previously Active Listeners"
  },
  {
    "artistName": "Angèle",
    "segment": "Previously Active Listeners"
  },
  {
    "artistName": "Soner Sarıkabadayı",
    "segment": "Moderate listeners"
  },
  {
    "artistName": "Şanışer",
    "segment": "Moderate listeners"
  },
  {
    "artistName": "Midnight Daydream",
    "segment": "Super Listeners"
  },
  {
    "artistName": "21 Savage",
    "segment": "Previously Active Listeners"
  },
  {
    "artistName": "Muti",
    "segment": "Previously Active Listeners"
  },
  {
    "artistName": "KOFE BUX",
    "segment": "Previously Active Listeners"
  },
  {
    "artistName": "Mal Waldron",
    "segment": "Moderate listeners"
  },
  {
    "artistName": "Mohito",
    "segment": "Previously Active Listeners"
  },
  {
    "artistName": "Pochill",
    "segment": "Previously Active Listeners"
  },
  {
    "artistName": "Lvbel C5",
    "segment": "Previously Active Listeners"
  },
  {
    "artistName": "De Jeugd Van Tegenwoordig",
    "segment": "Previously Active Listeners"
  },
  {
    "artistName": "Azet",
    "segment": "Moderate listeners"
  },
  {
    "artistName": "Eminem",
    "segment": "Previously Active Listeners"
  },
  {
    "artistName": "Hande Yener",
    "segment": "Light listeners"
  },
  {
    "artistName": "Esmeray",
    "segment": "Previously Active Listeners"
  },
  {
    "artistName": "Cut Off",
    "segment": "Previously Active Listeners"
  },
  {
    "artistName": "Bremer/McCoy",
    "segment": "Moderate listeners"
  }
]